tessdb/__init__.py
tessdb/reports/__init__.py
tessdb/reports/_version.py
tessdb/reports/geolist.py
tessdb/reports/ida/__init__.py
tessdb/reports/ida/ida.py
tessdb/reports/ida/metadata.py
tessdb/reports/ida/readings.py
tessdb/reports/ida/templates/IDA-template-4c.j2
tessdb/reports/ida/templates/__init__.py
tessdb_reports-3.7.19.data/scripts/tess_geolist.sh
tessdb_reports-3.7.19.data/scripts/tess_ida_pipeline
tessdb_reports-3.7.19.data/scripts/tess_readings_unassigned.sh
tessdb_reports-3.7.19.dist-info/licenses/LICENSE
tessdb_reports-3.7.19.dist-info/METADATA
tessdb_reports-3.7.19.dist-info/WHEEL
tessdb_reports-3.7.19.dist-info/entry_points.txt
tessdb_reports-3.7.19.dist-info/top_level.txt
tessdb_reports-3.7.19.dist-info/RECORD
