Metadata-Version: 2.4
Name: tessdb-reports
Version: 3.7.19
Summary: TESS datadabase report tools
Author-email: Rafael González <rafael08@ucm.es>
Project-URL: Homepage, https://github.com/STARS4ALL/tessdb-reports
Project-URL: Repository, https://github.com/STARS4ALL/tessdb-reports.git
Classifier: Programming Language :: Python :: 3.9
Classifier: Programming Language :: Python :: 3.10
Classifier: Programming Language :: Python :: 3.11
Classifier: Programming Language :: Python :: 3.12
Classifier: Programming Language :: SQL
Classifier: Development Status :: 4 - Beta
Classifier: Environment :: Console
Classifier: Operating System :: POSIX :: Linux
Classifier: Topic :: Scientific/Engineering :: Astronomy
Classifier: Topic :: Scientific/Engineering :: Atmospheric Science
Classifier: Intended Audience :: Science/Research
Classifier: Intended Audience :: Developers
Classifier: Natural Language :: English
Classifier: Natural Language :: Spanish
Requires-Python: >=3.9
License-File: LICENSE
Requires-Dist: python-decouple
Requires-Dist: python-dateutil
Requires-Dist: pytz
Requires-Dist: lica[jinja]
Provides-Extra: test
Requires-Dist: pytest>=6; extra == "test"
Dynamic: license-file
